LICENSE
MANIFEST.in
README.md
pyproject.toml
setup.cfg
setup.py
versioneer.py
./docs/conf.py
./nnapec/__init__.py
./nnapec/_version.py
./nnapec/nnapec.py
./nnapec/data/log_theme.ini
./nnapec/data/nn_apec.h5
./nnapec/test/conftest.py
./nnapec/test/test_basic.py
./nnapec/utils/__init__.py
./nnapec/utils/configuration.py
./nnapec/utils/logging.py
./nnapec/utils/package_data.py
nnapec/_version.py
nnapec.egg-info/PKG-INFO
nnapec.egg-info/SOURCES.txt
nnapec.egg-info/dependency_links.txt
nnapec.egg-info/requires.txt
nnapec.egg-info/top_level.txt
nnapec/data/log_theme.ini
nnapec/data/nn_apec.h5