Metadata-Version: 2.1
Name: nnapec
Version: 0.1.1
Summary: An emulator for the APEC model
Home-page: https://github.com/grburgess/nnapec
Author: J. Michael Burgess
Author-email: jburgess@mpe.mpg.de
License: GPL-2+
Project-URL: Bug Tracker, https://github.com/grburgess/nnapec/issues
Project-URL: Source Code, https://github.com/grburgess/nnapec
Classifier: Development Status :: 2 - Pre-Alpha
Classifier: Environment :: Console
Classifier: Intended Audience :: Science/Research
Classifier: License :: OSI Approved :: GNU General Public License v2 or later (GPLv2+)
Classifier: Operating System :: POSIX
Classifier: Programming Language :: Python :: 3.7
Classifier: Programming Language :: Python :: 3.8
Classifier: Programming Language :: Python :: 3.9
Classifier: Programming Language :: Python :: 3.10
Classifier: Topic :: Scientific/Engineering :: Physics
License-File: LICENSE
